{
  "qProperty": {
    "qInfo": {
      "qId": "523b5609-3267-414f-9c52-823e752e2362",
      "qType": "sheet"
    },
    "qMetaDef": {
      "title": "My new sheet",
      "description": ""
    },
    "rank": 1,
    "thumbnail": {
      "qStaticContentUrlDef": {}
    },
    "columns": 24,
    "rows": 12,
    "cells": [],
    "qChildListDef": {
      "qData": {
        "title": "/title"
      }
    },
    "gridResolution": "small",
    "layoutOptions": {
      "mobileLayout": "LIST"
    }
  },
  "qChildren": []
}